RxnIM/__init__.py
RxnIM/getReaction.py
RxnIM/main.py
RxnIM/rxnim.py
RxnIM/reaction/__init__.py
RxnIM/reaction/data.py
RxnIM/reaction/dataset.py
RxnIM/reaction/evaluate.py
RxnIM/reaction/interface.py
RxnIM/reaction/loss.py
RxnIM/reaction/model.py
RxnIM/reaction/tokenizer.py
RxnIM/reaction/transforms.py
RxnIM/reaction/utils.py
RxnIM/reaction/inference/__init__.py
RxnIM/reaction/inference/beam_search.py
RxnIM/reaction/inference/decode_strategy.py
RxnIM/reaction/inference/greedy_search.py
RxnIM/reaction/pix2seq/__init__.py
RxnIM/reaction/pix2seq/attention_layer.py
RxnIM/reaction/pix2seq/backbone.py
RxnIM/reaction/pix2seq/misc.py
RxnIM/reaction/pix2seq/pix2seq.py
RxnIM/reaction/pix2seq/position_encoding.py
RxnIM/reaction/pix2seq/transformer.py
RxnIM/reaction/transformer/__init__.py
RxnIM/reaction/transformer/decoder.py
RxnIM/reaction/transformer/embedding.py
RxnIM/reaction/transformer/swin_transformer.py
molscribe/__init__.py
molscribe/augment.py
molscribe/chemistry.py
molscribe/constants.py
molscribe/dataset.py
molscribe/evaluate.py
molscribe/interface.py
molscribe/loss.py
molscribe/model.py
molscribe/tokenizer.py
molscribe/utils.py
molscribe/indigo/__init__.py
molscribe/indigo/bingo.py
molscribe/indigo/inchi.py
molscribe/indigo/renderer.py
molscribe/inference/__init__.py
molscribe/inference/beam_search.py
molscribe/inference/decode_strategy.py
molscribe/inference/greedy_search.py
molscribe/transformer/__init__.py
molscribe/transformer/decoder.py
molscribe/transformer/embedding.py
molscribe/transformer/swin_transformer.py
RxnIM-1.3.dist-info/LICENSE.txt
RxnIM-1.3.dist-info/METADATA
RxnIM-1.3.dist-info/WHEEL
RxnIM-1.3.dist-info/top_level.txt
RxnIM-1.3.dist-info/RECORD
